nvs_sqa/__init__.py
nvs_sqa/quality_assessor.py
nvs_sqa/utils.py
nvs_sqa/checkpoints/v0.0.1/models/SeqModel_TransEncoder_rgb_viewsz(192)_lowfeat(24+48+96)_fviewsz(360)_pretr(0)_fuse(last)angsz(384)_nlyr(2)_v0.0.1_100.pth
nvs_sqa/checkpoints/v0.0.1/models/SeqModel_TransEncoder_rgb_viewsz(192)_lowfeat(24+48+96)_fviewsz(360)_pretr(0)_fuse(last)angsz(384)_nlyr(2)_v0.0.1_config.json
nvs_sqa/checkpoints/v0.0.1/regr/linear_regr.pkl
nvs_sqa/models/__init__.py
nvs_sqa/models/encoders.py
nvs_sqa/models/qa_methods.py
nvs_sqa/models/sequence_models.py
nvs_sqa/models/spatio_temporal_model.py
nvs_sqa-0.1.1.dist-info/LICENSE
nvs_sqa-0.1.1.dist-info/METADATA
nvs_sqa-0.1.1.dist-info/WHEEL
nvs_sqa-0.1.1.dist-info/top_level.txt
nvs_sqa-0.1.1.dist-info/RECORD
