Metadata-Version: 2.1
Name: nvs-sqa
Version: 0.1.1
Summary: No-reference quality assessment for neurally synthesized scenes
Home-page: https://github.com/VincentQQu/nvs_sqa
Author: Vincent Qu
Author-email: vincent.qu.cs@gmail.com
License: UNKNOWN
Platform: UNKNOWN
Classifier: Programming Language :: Python :: 3
Classifier: License :: CC0 1.0 Universal (CC0 1.0) Public Domain Dedication
Classifier: Operating System :: OS Independent
Requires-Python: >=3.6
License-File: LICENSE
Requires-Dist: numpy
Requires-Dist: torch (>=1.7.0)
Requires-Dist: torchvision (>=0.8.0)
Requires-Dist: scikit-learn
Requires-Dist: pillow
